Workbook

Sheet Master Checklist
A1: QUANTANA FRAUD DETECTION CHECKLIST
A2: Pre-Binding Submission Fraud Indicators by Document Type
A4: Document Type | B4: Check Category | C4: Specific Fraud Indicator | D4: What to Cross-Reference | E4: Severity | F4: Detection Method | G4: AI Implementation Notes
A5: ACORD 125
A6: ACORD 125 (Commercial App) | B6: Revenue Validation | C6: Revenue on application differs from financial statements by >15% | D6: Financial statements, tax returns (Schedule C / Form 1120) | E6: CRITICAL | F6: Cross-doc NLP | G6: Extract revenue fields, fuzzy-match across docs. Flag variance >15%.
B7: Revenue Validation | C7: Revenue figures are suspiciously round (exact multiples of $100K) | D7: Industry benchmarks, prior year applications | E7: HIGH | F7: Statistical | G7: Round-number detection algorithm on all currency fields.
B8: Loss History | C8: Application claims 'no prior losses' but loss runs show claims | D8: Loss runs, CLUE reports, E-Mod worksheets | E8: CRITICAL | F8: Cross-doc NLP | G8: Boolean match: app loss disclosure vs. loss run claim count.
B9: Loss History | C9: Gaps in prior coverage >30 days with no explanation | D9: Prior carrier COIs, loss runs | E9: HIGH | F9: Temporal | G9: Date-gap analysis on coverage periods.
B10: Metadata | C10: PDF creation date is after submission date | D10: Submission email timestamp | E10: HIGH | F10: Forensic | G10: Extract PDF metadata; compare creation_date vs. email receipt.
B11: Metadata | C11: Multiple PDF producers in single form (cut-and-paste assembly) | D11: Standard ACORD form templates | E11: MEDIUM | F11: Forensic | G11: Parse /Producer tags in PDF metadata per page.
B12: Metadata | C12: Font inconsistencies between applicant-filled and agent-filled sections | D12: Expected ACORD form fonts | E12: MEDIUM | F12: Forensic | G12: Font extraction and consistency check across form regions.
B13: Entity | C13: Business incorporated <2 years with mature operations claimed | D13: Secretary of State records, business credit databases | E13: HIGH | F13: Entity Intel | G13: API call to SOS database; compare incorporation date to app date.
B14: Entity | C14: Registered agent address is virtual office or PO box | D14: Google Maps API, USPS address validation | E14: MEDIUM | F14: Entity Intel | G14: Address classification model (residential/commercial/virtual).
B15: Statistical | C15: 25%+ of submissions from same agent fall outside appetite | D15: Portfolio-level submission analytics | E15: MEDIUM | F15: Pattern | G15: Agent-level submission quality scoring over time.
A16: ACORD 130
A17: ACORD 130 (Workers' Comp) | B17: Payroll Manipulation | C17: Total payroll on app differs from Form 941 quarterly totals by >10% | D17: Form 941 (quarterly), Form 940 (annual), W-2 totals | E17: CRITICAL | F17: Cross-doc NLP | G17: OCR payroll fields from tax docs; sum and compare to app.
B18: Payroll Manipulation | C18: Payroll per employee outside industry norms (e.g., <$25K or >$80K for classification) | D18: BLS industry wage data, NCCI classification guides | E18: HIGH | F18: Statistical | G18: Payroll-per-head calculation vs. industry lookup table.
B19: Classification Fraud | C19: High-hazard employees (laborers, roofers) classified as office/clerical | D19: Job descriptions, OSHA records, prior apps | E19: CRITICAL | F19: NLP + Rules | G19: Compare classification codes to business description keywords.
B20: Classification Fraud | C20: Payroll disproportionately allocated to lowest-risk classification | D20: Industry payroll mix benchmarks | E20: HIGH | F20: Statistical | G20: Classification-mix analysis vs. industry norms.
B21: Ghost Employees | C21: Employee count on app doesn't match W-2 count or 941 headcount | D21: W-2 transmittals, Form 941 employee counts | E21: HIGH | F21: Cross-doc NLP | G21: Headcount reconciliation across documents.
B22: E-Mod | C22: E-Mod worksheet claims don't match loss runs | D22: Loss runs from prior carriers, NCCI records | E22: CRITICAL | F22: Cross-doc NLP | G22: Claim-by-claim matching between E-Mod and loss runs.
B23: Temporal | C23: Employees added/removed coinciding exactly with policy inception | D23: Prior period payroll records | E23: MEDIUM | F23: Temporal | G23: Spike detection in headcount around renewal dates.
A24: ACORD 140
A25: ACORD 140 (Property) | B25: Value Overstatement | C25: Insured value exceeds comparable properties by >30% | D25: Tax assessor records, Zillow/Redfin data, prior carrier declarations | E25: CRITICAL | F25: Statistical | G25: API pull assessed values; ratio analysis (insured/assessed).
B26: Value Overstatement | C26: Contents value is disproportionate to building size and operations type | D26: Industry contents-to-building ratios (retail 20-40%, mfg 30-60%) | E26: HIGH | F26: Statistical | G26: Contents:building ratio vs. industry lookup by classification.
B27: Value Overstatement | C27: Property values round to nearest $50K increments across all locations | D27: Mathematical pattern analysis | E27: MEDIUM | F27: Statistical | G27: Round-number detection on all value fields.
B28: Occupancy Fraud | C28: Property claimed as occupied but inspection/satellite shows vacancy | D28: Google Earth imagery, inspection reports, utility records | E28: CRITICAL | F28: Visual AI | G28: Satellite image analysis for occupancy indicators.
B29: Condition Fraud | C29: 'Excellent' condition claimed for property visible as deteriorated in public imagery | D29: Google Street View, prior inspection reports | E29: HIGH | F29: Visual AI | G29: Image comparison model (claimed condition vs. public imagery).
B30: Temporal | C30: Property acquired recently with immediate high insured value | D30: Deed records, purchase price, closing documents | E30: HIGH | F30: Temporal | G30: Purchase date proximity analysis; value vs. purchase price ratio.
B31: Geographic | C31: Multiple properties at same address or physically impossible locations | D31: Address validation API, geolocation | E31: CRITICAL | F31: Rules | G31: Geocode all addresses; distance/duplicate check.
A32: Loss Runs
A33: Loss Runs (Prior Carriers) | B33: Fabrication | C33: Loss run appears entirely fabricated — claims not in carrier system | D33: Direct carrier verification, CLUE reports | E33: CRITICAL | F33: Cross-doc + API | G33: Carrier verification API or manual callback workflow.
B34: Fabrication | C34: Claim numbers don't match carrier's numbering format | D34: Known carrier claim number patterns | E34: CRITICAL | F34: Pattern | G34: Regex validation against carrier-specific claim ID formats.
B35: Omission | C35: Known claims in CLUE report missing from submitted loss runs | D35: CLUE reports, prior applications | E35: CRITICAL | F35: Cross-doc NLP | G35: Claim-count comparison: CLUE vs. submitted loss run.
B36: Alteration | C36: Loss dates shifted to fall outside the 3-5 year lookback period | D36: CLUE reports, E-Mod worksheets | E36: HIGH | F36: Temporal | G36: Date alignment check across all claim data sources.
B37: Metadata | C37: PDF author/producer doesn't match carrier name (e.g., 'John_home' not 'Hartford_Systems') | D37: Known carrier PDF metadata signatures | E37: HIGH | F37: Forensic | G37: PDF producer matching against carrier template database.
B38: Metadata | C38: Loss run is an embedded image (not searchable text) — prevents OCR verification | D38: Expected carrier output format | E38: MEDIUM | F38: Forensic | G38: Text-layer detection in PDF; flag image-only docs.
B39: Statistical | C39: All losses settle at amounts just below deductible (pattern fraud) | D39: Deductible schedule, claim severity distribution | E39: HIGH | F39: Statistical | G39: Clustering analysis on claim amounts vs. deductible thresholds.
B40: Statistical | C40: Claims clustering around policy inception or renewal dates | D40: Policy effective/expiration dates | E40: HIGH | F40: Temporal | G40: Date proximity scoring for claim dates vs. policy dates.
B41: Temporal | C41: Loss run effective date is before the policy effective date (impossible) | D41: Policy inception date | E41: CRITICAL | F41: Rules | G41: Simple date comparison rule.
A42: Financial Stmts
A43: Financial Statements (Audited/Unaudited) | B43: Revenue Fraud | C43: Revenue growth >30% YoY without business explanation | D43: Prior year financials, industry growth rates | E43: HIGH | F43: Statistical | G43: YoY growth calculation; flag outliers vs. industry median.
B44: Revenue Fraud | C44: Days Sales Outstanding (DSO) growing >20% while revenue increases (fictitious revenue) | D44: A/R aging, prior year DSO | E44: CRITICAL | F44: Ratio Analysis | G44: DSO trend calculation across 3 years.
B45: Revenue Fraud | C45: Accounts Receivable >40% of revenue | D45: Industry A/R benchmarks | E45: HIGH | F45: Ratio Analysis | G45: A/R-to-revenue ratio with industry comparison.
B46: Expense Anomaly | C46: COGS as % of revenue deviates >15% from industry norm | D46: Industry COGS benchmarks (mfg 40-60%, retail 50-70%) | E46: HIGH | F46: Ratio Analysis | G46: COGS margin vs. NAICS-code industry benchmark.
B47: Profitability | C47: Net profit margin exceeds industry average by >50% | D47: Industry profit margin data | E47: MEDIUM | F47: Statistical | G47: Margin comparison to peer group.
B48: GAAP Violation | C48: Large year-end journal entries >5% of net income | D48: Monthly trial balance, audit adjustments | E48: HIGH | F48: Statistical | G48: Adjustment magnitude analysis.
B49: Auditor Fraud | C49: Auditor not found in regulatory licensing database | D49: PCAOB database, state CPA board | E49: CRITICAL | F49: Entity Intel | G49: Auditor name lookup against PCAOB registered firms.
B50: Metadata | C50: Financial statement PDF creation date is months after fiscal year end | D50: Fiscal year end date, filing dates | E50: MEDIUM | F50: Forensic | G50: PDF creation date vs. stated period-end.
B51: Cross-doc | C51: Revenue on financials differs from ACORD 125 by >10% | D51: ACORD 125 application | E51: CRITICAL | F51: Cross-doc NLP | G51: Revenue extraction from both docs; variance calculation.
A52: COIs
A53: Certificates of Insurance (COIs) | B53: Forgery | C53: Insurer confirms no policy exists for stated policy number | D53: Direct insurer verification, NAIC database | E53: CRITICAL | F53: API + Manual | G53: Policy verification API or auto-generated verification request.
B54: Forgery | C54: ACORD logo is pixelated, low-res, or missing | D54: Standard ACORD 25 template | E54: HIGH | F54: Visual AI | G54: Logo detection and quality comparison model.
B55: Forgery | C55: Font inconsistencies between policy number, dates, and form body | D55: Expected ACORD 25 fonts and layout | E55: HIGH | F55: Forensic | G55: Font extraction and consistency scoring.
B56: Coverage Gap | C56: Policy expiration date is before application submission date | D56: Application submission timestamp | E56: CRITICAL | F56: Rules | G56: Simple date comparison.
B57: Coverage Gap | C57: Coverage limits inadequate for stated operations (e.g., $300K GL for $5M revenue) | D57: Operations description, revenue, industry minimums | E57: HIGH | F57: Rules + Stats | G57: Limit adequacy model by classification and revenue.
B58: Agent Fraud | C58: Agent email domain is generic (@gmail) or spoofed (amica-insurance.com vs. amica.com) | D58: Licensed agent database, domain verification | E58: HIGH | F58: Entity Intel | G58: Domain similarity scoring against known carrier domains.
B59: Agent Fraud | C59: Agent not found in state producer licensing database | D59: State DOI producer license lookup | E59: CRITICAL | F59: API | G59: NIPR API lookup for agent license status.
B60: Metadata | C60: COI PDF contains entire certificate as embedded image (no text layer) | D60: Standard COI output format | E60: MEDIUM | F60: Forensic | G60: Text layer presence check.
A61: Entity Docs
A62: Business Entity Documents | B62: Fabrication | C62: Entity not found in Secretary of State records | D62: State SOS database | E62: CRITICAL | F62: API | G62: Automated SOS API verification.
B63: Fabrication | C63: Articles of incorporation formatting doesn't match state template | D63: Known state filing templates | E63: HIGH | F63: Visual AI | G63: Template matching against state-specific formats.
B64: Thin File | C64: Business incorporated <2 years with no web presence | D64: SOS records, web presence check, Google search | E64: HIGH | F64: Entity Intel | G64: Age + web footprint scoring model.
B65: Thin File | C65: Federal EIN filed <6 months before application | D65: IRS EIN lookup | E65: HIGH | F65: Entity Intel | G65: EIN issuance date vs. application date.
B66: Ownership | C66: Same beneficial owner appears across multiple unrelated submissions | D66: Cross-MGA entity graph | E66: CRITICAL | F66: Network Graph | G66: Entity resolution + graph analysis across all submissions.
B67: Ownership | C67: Officers listed as 'To Be Determined' or nominee shareholders | D67: Filing documents | E67: MEDIUM | F67: NLP | G67: Named entity recognition on officer fields.
B68: Synthetic Entity | C68: Document watermarks/seals inconsistent with official state documents | D68: Known state seal library | E68: HIGH | F68: Visual AI | G68: Seal/watermark authenticity model.
B69: Metadata | C69: Document metadata author is personal name, not state filing system | D69: Expected state filing system metadata | E69: MEDIUM | F69: Forensic | G69: Producer/author field validation.
A70: Inspection / Photos
A71: Property Inspection Reports / Photos | B71: Photo Manipulation | C71: Copy-move or splicing detected in submitted photos | D71: Original image forensic analysis | E71: CRITICAL | F71: Visual AI | G71: Error Level Analysis (ELA) and copy-move detection model.
B72: Photo Manipulation | C72: EXIF GPS coordinates don't match claimed property address | D72: Property address geocoding | E72: CRITICAL | F72: Forensic | G72: EXIF GPS extraction; distance calculation to claimed address.
B73: Photo Manipulation | C73: EXIF data entirely stripped from photos (concealment indicator) | D73: Standard camera EXIF expectations | E73: HIGH | F73: Forensic | G73: EXIF presence check; flag completely stripped images.
B74: Photo Manipulation | C74: Reverse image search finds photo on internet / used in other claims | D74: Google Reverse Image Search API | E74: CRITICAL | F74: Visual AI | G74: Perceptual hashing + reverse image search.
B75: Condition Fraud | C75: Claimed 'excellent' condition contradicted by satellite/street imagery | D75: Google Earth, Google Street View (with timestamps) | E75: HIGH | F75: Visual AI | G75: Condition assessment model comparing submitted vs. public images.
B76: Occupancy Fraud | C76: Photos show vacant property but application claims occupied | D76: Application occupancy field | E76: CRITICAL | F76: Visual AI + NLP | G76: Vacancy indicators in photos (boarded windows, no furniture).
B77: Temporal | C77: Photo timestamps span only minutes for multi-hour inspection | D77: Expected inspection duration | E77: MEDIUM | F77: Forensic | G77: EXIF timestamp sequence analysis.
B78: Temporal | C78: Inspection report dated >6 months before application (stale) | D78: Application date | E78: MEDIUM | F78: Rules | G78: Date proximity check.
A79: Driver MVRs
A80: Driver MVRs (Motor Vehicle Records) | B80: Forgery | C80: MVR format doesn't match state DMV template | D80: Known state MVR templates | E80: CRITICAL | F80: Visual AI | G80: Template matching against state-specific formats.
B81: Omission | C81: Drivers with poor records omitted from fleet schedule | D81: CLUE reports, prior carrier records | E81: CRITICAL | F81: Cross-doc NLP | G81: Driver list comparison across all submitted documents.
B82: License Fraud | C82: Non-CDL driver operating commercial vehicle | D82: Vehicle schedule, license class | E82: HIGH | F82: Rules | G82: License class vs. vehicle type matching.
B83: Identity | C83: Driver name/DOB varies across MVR, application, and license | D83: All driver-related documents | E83: HIGH | F83: NLP | G83: Name and DOB fuzzy matching across document set.
B84: Temporal | C84: MVR dated >30 days before application (stale record) | D84: Application date | E84: MEDIUM | F84: Rules | G84: Date proximity check.
B85: Metadata | C85: MVR PDF metadata shows non-DMV producer | D85: Known DMV system identifiers | E85: HIGH | F85: Forensic | G85: PDF producer validation against DMV signatures.
A86: SOVs
A87: Schedules of Values (SOVs) | B87: Value Inflation | C87: Line-item costs significantly exceed contractor bid documents | D87: Original bid/contract, subcontractor quotes | E87: CRITICAL | F87: Cross-doc NLP | G87: Line-item extraction and comparison to contract values.
B88: Value Inflation | C88: Material quantities exceed project requirements | D88: Project plans, specifications | E88: HIGH | F88: Statistical | G88: Quantity reasonableness check vs. project scope.
B89: Fictitious Vendor | C89: Subcontractors on SOV cannot be verified in business registries | D89: SOS records, contractor license databases | E89: CRITICAL | F89: Entity Intel | G89: Automated vendor verification across registries.
B90: Phase Fraud | C90: Early phases allocated disproportionate percentage (front-loading) | D90: Industry phase allocation norms | E90: HIGH | F90: Statistical | G90: Phase allocation analysis vs. construction benchmarks.
B91: Ghost Labor | C91: Labor costs allocated to phases with no corresponding worker records | D91: Payroll records, W-2 data | E91: CRITICAL | F91: Cross-doc NLP | G91: Labor cost vs. payroll reconciliation.
A92: Surplus Lines
A93: Surplus Lines Filings | B93: Regulatory | C93: Carrier not on state-approved surplus lines list | D93: State DOI surplus lines carrier list | E93: CRITICAL | F93: API | G93: Carrier lookup against state-specific approved lists.
B94: Regulatory | C94: False 'unavailable in admitted market' affidavit — coverage was available | D94: Admitted market carrier quotes | E94: CRITICAL | F94: Cross-doc NLP | G94: Check for competing admitted market quotes in submission.
B95: Tax Fraud | C95: Surplus lines tax not calculated or remitted (typically 3-5%) | D95: State tax requirements, premium calculations | E95: HIGH | F95: Rules | G95: Tax calculation verification against state rates.
B96: Temporal | C96: Filing retroactive to policy inception (improper timing) | D96: Policy effective date, filing date | E96: HIGH | F96: Temporal | G96: Filing date vs. inception date comparison.
A97: Prof. Licenses
A98: Professional Licenses / Certs | B98: Forgery | C98: License number not found in issuing authority database | D98: State licensing board databases | E98: CRITICAL | F98: API | G98: Automated license verification against state boards.
B99: Expired/Suspended | C99: License expired or suspended but represented as active | D99: Licensing authority status check | E99: CRITICAL | F99: API | G99: Real-time license status verification.
B100: Scope Mismatch | C100: License type doesn't cover stated scope of work | D100: License classification, stated services | E100: HIGH | F100: Rules + NLP | G100: License scope vs. service description matching.
B101: Discipline | C101: Undisclosed disciplinary actions on license | D101: State board disciplinary records | E101: HIGH | F101: API | G101: Disciplinary record check against board databases.
...

Sheet Cross-Doc Validation
A1: CROSS-DOCUMENT VALIDATION MATRIX
A2: What to compare against what — and when to flag it
A4: Validation Area | B4: Source Document(s) | C4: Compare Against | D4: Acceptable Variance | E4: Flag Threshold | F4: Action if Flagged
A5: Revenue | B5: ACORD 125 revenue field | C5: Financial statements (income stmt) | D5: ±10% | E5: >15% = HIGH >25% = CRITICAL | F5: Escalate to SIU; request tax returns for reconciliation
A6: Revenue | B6: Financial statements | C6: Tax returns (Sched C / 1120) | D6: ±5% | E6: >10% = HIGH >20% = CRITICAL | F6: Request explanation; compare against bank statements
A7: Payroll (WC) | B7: ACORD 130 total payroll | C7: Form 941 quarterly totals (sum) | D7: ±$500 | E7: >$2,000 = HIGH >10% = CRITICAL | F7: Payroll audit trigger; request W-2 transmittals
A8: Payroll (WC) | B8: ACORD 130 by classification | C8: BLS wage data by job code | D8: Within industry range | E8: Per-head <$25K or >$80K for class = HIGH | F8: Classification review; request job descriptions
A9: Employee Count | B9: ACORD 125/130 headcount | C9: W-2 count, Form 941 count | D9: ±1 employee | E9: >2 employees = HIGH | F9: Ghost employee investigation
A10: Loss History | B10: Loss runs (submitted) | C10: CLUE reports | D10: Exact match on claim count | E10: Any omitted claim = CRITICAL | F10: Direct carrier verification of all claims
A11: Loss History | B11: ACORD 125 loss disclosure | C11: Loss runs + CLUE | D11: Consistent | E11: Any undisclosed loss = HIGH | F11: Escalate; request loss run directly from carrier
A12: Loss History | B12: E-Mod worksheet claims | C12: Loss runs from carriers | D12: Claim-by-claim match | E12: Any mismatch = HIGH | F12: NCCI verification; carrier callback
A13: Property Values | B13: ACORD 140 insured values | C13: Tax assessor records | D13: Insured = 1.3-1.5x assessed | E13: >2x assessed = HIGH >3x = CRITICAL | F13: Independent appraisal required
A14: Property Values | B14: ACORD 140 contents value | C14: Building value x industry ratio | D14: Retail 20-40%, Mfg 30-60% | E14: Ratio outside range = HIGH | F14: Contents inventory required
A15: Property Condition | B15: Inspection report condition | C15: Google Earth / Street View | D15: Consistent | E15: Visible contradiction = HIGH | F15: Physical re-inspection required
... A24: Surplus Lines | B24: Affidavit of unavailability | C24: Admitted market quotes in file | D24: No admitted coverage available | E24: Admitted quotes present = CRITICAL | F24: Regulatory filing review; report to DOI

Sheet Detection Methods
A1: DETECTION METHOD TAXONOMY
A3: Method | B3: Description | C3: Example Use Cases | D3: Implementation Phase
A4: Cross-doc NLP | B4: Natural language processing to extract and compare data fields across multiple documents | C4: Revenue matching (app vs. financials), payroll reconciliation (app vs. 941), loss count comparison | D4: Phase 1 (MVP)
A5: Forensic | B5: PDF metadata analysis, font extraction, image forensics, producer tag validation | C5: PDF creation date validation, font consistency checks, author/producer verification | D5: Phase 1 (MVP)
A6: Rules | B6: Deterministic business rules and date/value comparisons | C6: Coverage date validation, license class matching, geographic impossibility checks | D6: Phase 1 (MVP)
A7: Statistical | B7: Anomaly detection, ratio analysis, round-number detection, industry benchmark comparison | C7: Revenue growth outliers, payroll-per-head analysis, value-to-assessed ratio | D7: Phase 1 (MVP)
A8: Temporal | B8: Date sequence analysis, proximity scoring, gap detection | C8: Coverage gaps, claim timing clusters, filing date validation | D8: Phase 1 (MVP)
A9: Entity Intel | B9: Business registry verification, web presence scoring, address classification | C9: SOS lookup, EIN validation, thin-file scoring, virtual office detection | D9: Phase 2
A10: Visual AI | B10: Computer vision for document template matching, photo manipulation detection, condition assessment | C10: ELA analysis, EXIF verification, satellite comparison, seal authenticity | D10: Phase 2
A11: NLP | B11: Intent detection, sentiment analysis, concealment language detection in narratives | C11: Broker pressure language, urgency detection, omission identification in cover letters | D11: Phase 2
A12: API | B12: Direct verification against authoritative external databases | C12: Carrier policy verification, DMV lookup, NIPR license check, NHTSA VIN decoder | D12: Phase 2
A13: Network Graph | B13: Cross-submission entity resolution and relationship mapping | C13: Fraud ring detection, shared beneficial owners, repeated agent patterns | D13: Phase 3 (Moat)
A14: Pattern | B14: Longitudinal pattern analysis across submissions and time | C14: Agent submission quality trends, claim timing patterns, seasonal anomalies | D14: Phase 3
A15: Ratio Analysis | B15: Financial ratio calculations with industry comparison | C15: DSO trends, COGS margins, A/R-to-revenue, profit margin benchmarking | D15: Phase 1 (MVP)

Sheet Severity Framework
A1: SEVERITY CLASSIFICATION FRAMEWORK
A3: Severity | B3: Definition | C3: Required Action | D3: SLA / Response Time
A4: CRITICAL | B4: Document appears forged or fabricated. Material fact concealment with clear fraudulent intent. Cross-document discrepancies >30%. Identity fraud indicators. | C4: Immediate escalation to SIU. Submission hold. Direct verification with carrier/authority. Consider filing SAR. | D4: < 2 hours
A5: HIGH | B5: Significant misrepresentation (15-30% discrepancy). Material omissions. Classification fraud. License/credential failures. Metadata tampering detected. | C5: Escalate to senior underwriter + SIU review queue. Request additional documentation. Enhanced due diligence. | D5: < 24 hours
A6: MEDIUM | B6: Discrepancies 5-15% with reasonable explanations possible. Minor documentation gaps. Metadata anomalies with alternative explanations. | C6: Flag for underwriter review. Request clarification or additional supporting documents. Conditional approval gate. | D6: < 48 hours
A7: LOW | B7: Formatting inconsistencies. Minor font/style variations. Non-critical field discrepancies. Information quality issues not affecting content. | C7: Log for pattern analysis. No action required on individual submission. Aggregate for agent quality scoring. | D7: Informational only

Sheet Summary
A1: CHECKLIST SUMMARY
A3: Metric | B3: CRITICAL | C3: HIGH | D3: MEDIUM | E3: LOW | F3: Total
A4: Total Fraud Indicators | B4: =COUNTIF('Master Checklist'!E:E,"CRITICAL") -> 39 | C4: =COUNTIF('Master Checklist'!E:E,"HIGH") -> 47 | D4: =COUNTIF('Master Checklist'!E:E,"MEDIUM") -> 19 | E4: =COUNTIF('Master Checklist'!E:E,"LOW") -> 0 | F4: =SUM(B4:E4) -> 105
A6: By Document Type
A7: Document Type | B7: CRITICAL | C7: HIGH | D7: MEDIUM | E7: LOW | F7: Total
A8: ACORD 125 | B8: =COUNTIFS('Master Checklist'!A:A,"*ACORD 125*",'Master Checklist'!E:E,"CRITICAL") -> 1 | C8: =COUNTIFS('Master Checklist'!A:A,"*ACORD 125*",'Master Checklist'!E:E,"HIGH") -> 0 | D8: =COUNTIFS('Master Checklist'!A:A,"*ACORD 125*",'Master Checklist'!E:E,"MEDIUM") -> 0 | E8: =COUNTIFS('Master Checklist'!A:A,"*ACORD 125*",'Master Checklist'!E:E,"LOW") -> 0 | F8: =SUM(B8:E8) -> 1
A9: ACORD 130 | B9: =COUNTIFS('Master Checklist'!A:A,"*ACORD 130*",'Master Checklist'!E:E,"CRITICAL") -> 1 | C9: =COUNTIFS('Master Checklist'!A:A,"*ACORD 130*",'Master Checklist'!E:E,"HIGH") -> 0 | D9: =COUNTIFS('Master Checklist'!A:A,"*ACORD 130*",'Master Checklist'!E:E,"MEDIUM") -> 0 | E9: =COUNTIFS('Master Checklist'!A:A,"*ACORD 130*",'Master Checklist'!E:E,"LOW") -> 0 | F9: =SUM(B9:E9) -> 1
A10: ACORD 140 | B10: =COUNTIFS('Master Checklist'!A:A,"*ACORD 140*",'Master Checklist'!E:E,"CRITICAL") -> 1 | C10: =COUNTIFS('Master Checklist'!A:A,"*ACORD 140*",'Master Checklist'!E:E,"HIGH") -> 0 | D10: =COUNTIFS('Master Checklist'!A:A,"*ACORD 140*",'Master Checklist'!E:E,"MEDIUM") -> 0 | E10: =COUNTIFS('Master Checklist'!A:A,"*ACORD 140*",'Master Checklist'!E:E,"LOW") -> 0 | F10: =SUM(B10:E10) -> 1
A11: Loss Runs | B11: =COUNTIFS('Master Checklist'!A:A,"*Loss Runs*",'Master Checklist'!E:E,"CRITICAL") -> 1 | C11: =COUNTIFS('Master Checklist'!A:A,"*Loss Runs*",'Master Checklist'!E:E,"HIGH") -> 0 | D11: =COUNTIFS('Master Checklist'!A:A,"*Loss Runs*",'Master Checklist'!E:E,"MEDIUM") -> 0 | E11: =COUNTIFS('Master Checklist'!A:A,"*Loss Runs*",'Master Checklist'!E:E,"LOW") -> 0 | F11: =SUM(B11:E11) -> 1
A12: Financial Statements | B12: =COUNTIFS('Master Checklist'!A:A,"*Financial Statements*",'Master Checklist'!E:E,"CRITICAL") -> 0 | C12: =COUNTIFS('Master Checklist'!A:A,"*Financial Statements*",'Master Checklist'!E:E,"HIGH") -> 1 | D12: =COUNTIFS('Master Checklist'!A:A,"*Financial Statements*",'Master Checklist'!E:E,"MEDIUM") -> 0 | E12: =COUNTIFS('Master Checklist'!A:A,"*Financial Statements*",'Master Checklist'!E:E,"LOW") -> 0 | F12: =SUM(B12:E12) -> 1
A13: Certificates of | B13: =COUNTIFS('Master Checklist'!A:A,"*Certificates of*",'Master Checklist'!E:E,"CRITICAL") -> 1 | C13: =COUNTIFS('Master Checklist'!A:A,"*Certificates of*",'Master Checklist'!E:E,"HIGH") -> 0 | D13: =COUNTIFS('Master Checklist'!A:A,"*Certificates of*",'Master Checklist'!E:E,"MEDIUM") -> 0 | E13: =COUNTIFS('Master Checklist'!A:A,"*Certificates of*",'Master Checklist'!E:E,"LOW") -> 0 | F13: =SUM(B13:E13) -> 1
A14: Business Entity | B14: =COUNTIFS('Master Checklist'!A:A,"*Business Entity*",'Master Checklist'!E:E,"CRITICAL") -> 1 | C14: =COUNTIFS('Master Checklist'!A:A,"*Business Entity*",'Master Checklist'!E:E,"HIGH") -> 0 | D14: =COUNTIFS('Master Checklist'!A:A,"*Business Entity*",'Master Checklist'!E:E,"MEDIUM") -> 0 | E14: =COUNTIFS('Master Checklist'!A:A,"*Business Entity*",'Master Checklist'!E:E,"LOW") -> 0 | F14: =SUM(B14:E14) -> 1
A15: Property Inspection | B15: =COUNTIFS('Master Checklist'!A:A,"*Property Inspection*",'Master Checklist'!E:E,"CRITICAL") -> 1 | C15: =COUNTIFS('Master Checklist'!A:A,"*Property Inspection*",'Master Checklist'!E:E,"HIGH") -> 0 | D15: =COUNTIFS('Master Checklist'!A:A,"*Property Inspection*",'Master Checklist'!E:E,"MEDIUM") -> 0 | E15: =COUNTIFS('Master Checklist'!A:A,"*Property Inspection*",'Master Checklist'!E:E,"LOW") -> 0 | F15: =SUM(B15:E15) -> 1
A16: Driver MVRs | B16: =COUNTIFS('Master Checklist'!A:A,"*Driver MVRs*",'Master Checklist'!E:E,"CRITICAL") -> 1 | C16: =COUNTIFS('Master Checklist'!A:A,"*Driver MVRs*",'Master Checklist'!E:E,"HIGH") -> 0 | D16: =COUNTIFS('Master Checklist'!A:A,"*Driver MVRs*",'Master Checklist'!E:E,"MEDIUM") -> 0 | E16: =COUNTIFS('Master Checklist'!A:A,"*Driver MVRs*",'Master Checklist'!E:E,"LOW") -> 0 | F16: =SUM(B16:E16) -> 1
A17: Schedules of | B17: =COUNTIFS('Master Checklist'!A:A,"*Schedules of*",'Master Checklist'!E:E,"CRITICAL") -> 1 | C17: =COUNTIFS('Master Checklist'!A:A,"*Schedules of*",'Master Checklist'!E:E,"HIGH") -> 0 | D17: =COUNTIFS('Master Checklist'!A:A,"*Schedules of*",'Master Checklist'!E:E,"MEDIUM") -> 0 | E17: =COUNTIFS('Master Checklist'!A:A,"*Schedules of*",'Master Checklist'!E:E,"LOW") -> 0 | F17: =SUM(B17:E17) -> 1
A18: Surplus Lines | B18: =COUNTIFS('Master Checklist'!A:A,"*Surplus Lines*",'Master Checklist'!E:E,"CRITICAL") -> 1 | C18: =COUNTIFS('Master Checklist'!A:A,"*Surplus Lines*",'Master Checklist'!E:E,"HIGH") -> 0 | D18: =COUNTIFS('Master Checklist'!A:A,"*Surplus Lines*",'Master Checklist'!E:E,"MEDIUM") -> 0 | E18: =COUNTIFS('Master Checklist'!A:A,"*Surplus Lines*",'Master Checklist'!E:E,"LOW") -> 0 | F18: =SUM(B18:E18) -> 1
A19: Professional | B19: =COUNTIFS('Master Checklist'!A:A,"*Professional*",'Master Checklist'!E:E,"CRITICAL") -> 1 | C19: =COUNTIFS('Master Checklist'!A:A,"*Professional*",'Master Checklist'!E:E,"HIGH") -> 0 | D19: =COUNTIFS('Master Checklist'!A:A,"*Professional*",'Master Checklist'!E:E,"MEDIUM") -> 0 | E19: =COUNTIFS('Master Checklist'!A:A,"*Professional*",'Master Checklist'!E:E,"LOW") -> 0 | F19: =SUM(B19:E19) -> 1
A20: Environmental | B20: =COUNTIFS('Master Checklist'!A:A,"*Environmental*",'Master Checklist'!E:E,"CRITICAL") -> 1 | C20: =COUNTIFS('Master Checklist'!A:A,"*Environmental*",'Master Checklist'!E:E,"HIGH") -> 0 | D20: =COUNTIFS('Master Checklist'!A:A,"*Environmental*",'Master Checklist'!E:E,"MEDIUM") -> 0 | E20: =COUNTIFS('Master Checklist'!A:A,"*Environmental*",'Master Checklist'!E:E,"LOW") -> 0 | F20: =SUM(B20:E20) -> 1
A21: Payroll Records | B21: =COUNTIFS('Master Checklist'!A:A,"*Payroll Records*",'Master Checklist'!E:E,"CRITICAL") -> 1 | C21: =COUNTIFS('Master Checklist'!A:A,"*Payroll Records*",'Master Checklist'!E:E,"HIGH") -> 0 | D21: =COUNTIFS('Master Checklist'!A:A,"*Payroll Records*",'Master Checklist'!E:E,"MEDIUM") -> 0 | E21: =COUNTIFS('Master Checklist'!A:A,"*Payroll Records*",'Master Checklist'!E:E,"LOW") -> 0 | F21: =SUM(B21:E21) -> 1
A22: Broker Submissions | B22: =COUNTIFS('Master Checklist'!A:A,"*Broker Submissions*",'Master Checklist'!E:E,"CRITICAL") -> 1 | C22: =COUNTIFS('Master Checklist'!A:A,"*Broker Submissions*",'Master Checklist'!E:E,"HIGH") -> 0 | D22: =COUNTIFS('Master Checklist'!A:A,"*Broker Submissions*",'Master Checklist'!E:E,"MEDIUM") -> 0 | E22: =COUNTIFS('Master Checklist'!A:A,"*Broker Submissions*",'Master Checklist'!E:E,"LOW") -> 0 | F22: =SUM(B22:E22) -> 1
A23: Fleet Schedules | B23: =COUNTIFS('Master Checklist'!A:A,"*Fleet Schedules*",'Master Checklist'!E:E,"CRITICAL") -> 0 | C23: =COUNTIFS('Master Checklist'!A:A,"*Fleet Schedules*",'Master Checklist'!E:E,"HIGH") -> 1 | D23: =COUNTIFS('Master Checklist'!A:A,"*Fleet Schedules*",'Master Checklist'!E:E,"MEDIUM") -> 0 | E23: =COUNTIFS('Master Checklist'!A:A,"*Fleet Schedules*",'Master Checklist'!E:E,"LOW") -> 0 | F23: =SUM(B23:E23) -> 1
A24: TOTAL | B24: =SUM(B8:B23) -> 14 | C24: =SUM(C8:C23) -> 2 | D24: =SUM(D8:D23) -> 0 | E24: =SUM(E8:E23) -> 0 | F24: =SUM(F8:F23) -> 16
A26: By Detection Method
A27: Detection Method | B27: Count
A28: Cross-doc NLP | B28: =COUNTIF('Master Checklist'!F:F,"*Cross-doc NLP*") -> 17
A29: Forensic | B29: =COUNTIF('Master Checklist'!F:F,"*Forensic*") -> 14
A30: Rules | B30: =COUNTIF('Master Checklist'!F:F,"*Rules*") -> 12
A31: Statistical | B31: =COUNTIF('Master Checklist'!F:F,"*Statistical*") -> 13
A32: Temporal | B32: =COUNTIF('Master Checklist'!F:F,"*Temporal*") -> 6
A33: Entity Intel | B33: =COUNTIF('Master Checklist'!F:F,"*Entity Intel*") -> 8
A34: Visual AI | B34: =COUNTIF('Master Checklist'!F:F,"*Visual AI*") -> 12
A35: NLP | B35: =COUNTIF('Master Checklist'!F:F,"*NLP*") -> 26
A36: API | B36: =COUNTIF('Master Checklist'!F:F,"*API*") -> 11
A37: Network Graph | B37: =COUNTIF('Master Checklist'!F:F,"*Network Graph*") -> 1
A38: Pattern | B38: =COUNTIF('Master Checklist'!F:F,"*Pattern*") -> 2
A39: Ratio Analysis | B39: =COUNTIF('Master Checklist'!F:F,"*Ratio Analysis*") -> 3
